TelnetCommander/__init__.py
TelnetCommander/telnet_commander.py
telnet_commander-0.0.3.dist-info/LICENSE
telnet_commander-0.0.3.dist-info/METADATA
telnet_commander-0.0.3.dist-info/WHEEL
telnet_commander-0.0.3.dist-info/top_level.txt
telnet_commander-0.0.3.dist-info/RECORD
